itertools_cli/__init__.py
itertools_cli/__main__.py
itertools_cli-0.1.1.dist-info/METADATA
itertools_cli-0.1.1.dist-info/WHEEL
itertools_cli-0.1.1.dist-info/entry_points.txt
itertools_cli-0.1.1.dist-info/RECORD
